{"rrWine": ["dangermice", "protoGuy", "soulofShi", "OnlytheTruth", "CentralBulletin", "roger_roger", "KronosStar", "HomelandIlluminations", "panopticon", "AbilaPost", "maha_Homeland", "megaMan"], "AbilaPost": ["blueSunshine", "microBanana", "worldWatcher", "courage4life", "klingon4real", "brain448", "electricAvenue", "dtennent", "joyce101", "jaques", "muppiesRock", "wireHead1122", "siliconKing", "sarajane", "stolkfair", "ninjabob", "henri", "soup4u", "dolls4sale", "plasticParts", "zengardener", "wiseWords", "rrWine", "vonneka", "brandonL", "phantomagate", "sithLordJames", "slamrjamr", "lindyT", "vetsRock", "gardener4958", "BlueVelvet", "lordWally", "dragonRider1", "farmboy", "teresaJ", "luvMyPants", "rnbwBrite", "pinky", "jgrobannne"], "pinky": ["NewsOnlineToday", "Officia1AbilaPost", "choconibbs", "CentralBulletin", "brewvebeenserved", "roger_roger", "HomelandIlluminations", "KronosStar", "truccotrucco", "cleaningFish", "AbilaAllFaith", "AbilaPost", "InternationalNews"], "BlueVelvet": ["NewsOnlineToday", "FriendsOfKronos", "sofitees", "POK", "CentralBulletin", "roger_roger", "HomelandIlluminations", "hempRules", "KronosStar", "truccotrucco", "GreyCatCollectibles", "writinLazy", "AbilaPost", "megaMan", "InternationalNews", "Viktor-E", "MindOfKronos", "ourcountryourrights"], "dragonRider1": ["prettyRain", "NewsOnlineToday", "FriendsOfKronos", "sofitees", "POK", "choconibbs", "CentralBulletin", "roger_roger", "HomelandIlluminations", "KronosStar", "truccotrucco", "AbilaPoliceDepartment", "AbilaPost", "MindOfKronos", "InternationalNews"], "MindOfKronos": ["BlueVelvet", "dragonRider1"], "blueSunshine": ["NewsOnlineToday", "truthforcadau", "Simon_Hamaeth", "CentralBulletin", "KronosStar", "HomelandIlluminations", "kingWilly", "AbilaPost", "maha_Homeland", "megaMan", "SaveOurWildlands", "Viktor-E", "InternationalNews"], "dtennent": ["NewsOnlineToday", "FriendsOfKronos", "OnlytheTruth", "CentralBulletin", "HomelandIlluminations", "trollingsnark", "GreyCatCollectibles", "AbilaPost", "megaMan", "AbilaFireDept"], "klingon4real": ["NewsOnlineToday", "OnlytheTruth", "POK", "choconibbs", "CentralBulletin", "HomelandIlluminations", "KronosStar", "AbilaPoliceDepartment", "AbilaPost", "megaMan", "ReggieWassali", "InternationalNews", "rockStar113"], "sarajane": ["protoGuy", "FriendsOfKronos", "sofitees", "junk99902", "martaflores", "POK", "CentralBulletin", "roger_roger", "HomelandIlluminations", "KronosStar", "truccotrucco", "AbilaPoliceDepartment", "AbilaPost", "SaveOurWildlands", "martaO", "InternationalNews", "pashmina887"], "wiseWords": ["POK", "martaO", "NewsOnlineToday", "choconibbs", "grlPwrz505", "omgponies", "footfingers", "AbilaPost", "praise111", "SaveOurWildlands", "InternationalNews", "protoGuy", "truccotrucco", "ourcountryourrights", "FriendsOfKronos", "HomelandIlluminations", "KronosStar", "trollingsnark", "megaMan"], "ourcountryourrights": ["wireHead1122", "BlueVelvet", "brain448", "plasticParts", "wiseWords", "joyce101", "vetsRock"], "phantomagate": ["NewsOnlineToday", "CentralBulletin", "KronosStar", "HomelandIlluminations", "grlPwrz505", "truccotrucco", "trollingsnark", "GreyCatCollectibles", "redisrad", "AbilaPost", "maha_Homeland", "megaMan", "AbilaFireDept", "InternationalNews"], "CentralBulletin": ["blueSunshine", "worldWatcher", "courage4life", "klingon4real", "brain448", "electricAvenue", "dtennent", "joyce101", "jaques", "wireHead1122", "siliconKing", "sarajane", "ninjabob", "stolkfair", "henri", "soup4u", "zengardener", "rrWine", "vonneka", "brandonL", "phantomagate", "sithLordJames", "slamrjamr", "lindyT", "vetsRock", "gardener4958", "BlueVelvet", "lordWally", "dragonRider1", "farmboy", "luvMyPants", "rnbwBrite", "pinky"], "teresaJ": ["dangermice", "NewsOnlineToday", "protoGuy", "HerraTomas", "SaveOurWildlands", "POK", "hennyhenhendrix", "KronosStar", "SiaradSea", "Sara_Nespola", "panopticon", "AbilaPost", "AbilaAllFaith", "AbilaFireDept"], "POK": ["BlueVelvet", "brandonL", "microBanana", "siliconKing", "sarajane", "dragonRider1", "teresaJ", "rnbwBrite", "luvMyPants", "courage4life", "klingon4real", "soup4u", "slamrjamr", "dolls4sale", "wiseWords", "joyce101"], "microBanana": ["NewsOnlineToday", "prettyRain", "FriendsOfKronos", "POK", "michelleR", "roger_roger", "HomelandIlluminations", "KronosStar", "truccotrucco", "AbilaPoliceDepartment", "AbilaPost", "AbilaFireDept", "GreyCatCollectibles", "MarcusDrymiau", "InternationalNews"], "siliconKing": ["protoGuy", "NewsOnlineToday", "FriendsOfKronos", "truthforcadau", "Simon_Hamaeth", "POK", "CentralBulletin", "roger_roger", "HomelandIlluminations", "KronosStar", "hempRules", "redisrad", "AbilaPost", "megaMan", "InternationalNews"], "vetsRock": ["dangermice", "FriendsOfKronos", "CentralBulletin", "hennyhenhendrix", "HomelandIlluminations", "KronosStar", "SiaradSea", "truccotrucco", "cleaningFish", "AbilaPost", "Viktor-E", "InternationalNews", "ourcountryourrights"], "wireHead1122": ["dangermice", "protoGuy", "NewsOnlineToday", "surferMan", "choconibbs", "CentralBulletin", "roger_roger", "KronosStar", "HomelandIlluminations", "truccotrucco", "AbilaAllFaith", "AbilaPost", "maha_Homeland", "Viktor-E", "InternationalNews", "ourcountryourrights"], "luvMyPants": ["protoGuy", "truthforcadau", "sofitees", "POK", "choconibbs", "CentralBulletin", "HomelandIlluminations", "KronosStar", "AbilaPost", "SaveOurWildlands", "Viktor-E", "InternationalNews"], "Viktor-E": ["blueSunshine", "BlueVelvet", "wireHead1122", "stolkfair", "luvMyPants", "brain448", "vonneka", "vetsRock"], "brain448": ["NewsOnlineToday", "FriendsOfKronos", "CentralBulletin", "KronosStar", "HomelandIlluminations", "Sara_Nespola", "footfingers", "AbilaPost", "panopticon", "ReggieWassali", "InternationalNews", "Viktor-E", "trapanitweets", "ourcountryourrights"], "InternationalNews": ["blueSunshine", "microBanana", "worldWatcher", "courage4life", "klingon4real", "brain448", "joyce101", "jaques", "muppiesRock", "wireHead1122", "siliconKing", "sarajane", "ninjabob", "stolkfair", "henri", "plasticParts", "zengardener", "wiseWords", "phantomagate", "slamrjamr", "vetsRock", "BlueVelvet", "lordWally", "dragonRider1", "rnbwBrite", "luvMyPants", "pinky", "jgrobannne"], "rnbwBrite": ["NewsOnlineToday", "FriendsOfKronos", "POK", "choconibbs", "CentralBulletin", "powercrystals", "brewvebeenserved", "KronosStar", "HomelandIlluminations", "truccotrucco", "onl1neRecords", "AbilaPost", "maha_Homeland", "megaMan", "martaO", "InternationalNews"], "choconibbs": ["gardener4958", "wireHead1122", "lordWally", "dragonRider1", "rnbwBrite", "henri", "luvMyPants", "klingon4real", "sithLordJames", "dolls4sale", "plasticParts", "zengardener", "wiseWords", "pinky", "lindyT"], "dolls4sale": ["protoGuy", "NewsOnlineToday", "sofitees", "OnlytheTruth", "POK", "choconibbs", "KronosStar", "HomelandIlluminations", "joyBubbles", "redisrad", "AbilaPost", "maha_Homeland", "GreyCatCollectibles"], "plasticParts": ["NewsOnlineToday", "FriendsOfKronos", "choconibbs", "HomelandIlluminations", "KronosStar", "SiaradSea", "hngohebo_ABILAPOST", "AbilaPost", "megaMan", "InternationalNews", "ourcountryourrights"], "FriendsOfKronos": ["jaques", "BlueVelvet", "siliconKing", "microBanana", "sarajane", "ninjabob", "farmboy", "stolkfair", "dragonRider1", "rnbwBrite", "brain448", "plasticParts", "zengardener", "wiseWords", "dtennent", "vetsRock"], "maha_Homeland": ["jaques", "gardener4958", "wireHead1122", "blueSunshine", "phantomagate", "rnbwBrite", "dolls4sale", "rrWine", "lindyT"], "truccotrucco": ["jaques", "BlueVelvet", "lordWally", "microBanana", "dragonRider1", "sarajane", "wireHead1122", "phantomagate", "electricAvenue", "rnbwBrite", "courage4life", "sithLordJames", "slamrjamr", "wiseWords", "jgrobannne", "pinky", "lindyT", "vetsRock"], "powercrystals": ["rnbwBrite"], "soup4u": ["OnlytheTruth", "POK", "michelleR", "CentralBulletin", "KronosStar", "HomelandIlluminations", "Sara_Nespola", "AbilaPost", "SaveOurWildlands"], "muppiesRock": ["HomelandIlluminations", "KronosStar", "dtrejos", "footfingers", "AbilaPost", "panopticon", "InternationalNews"], "gardener4958": ["choconibbs", "CentralBulletin", "KronosStar", "HomelandIlluminations", "redisrad", "AbilaPost", "maha_Homeland", "megaMan", "GreyCatCollectibles"], "sithLordJames": ["NewsOnlineToday", "prettyRain", "choconibbs", "CentralBulletin", "ernieO", "KronosStar", "HomelandIlluminations", "truccotrucco", "AbilaPost", "AbilaPoliceDepartment"], "lindyT": ["NewsOnlineToday", "choconibbs", "CentralBulletin", "HomelandIlluminations", "KronosStar", "truccotrucco", "AbilaPost", "maha_Homeland", "megaMan"], "lordWally": ["prettyRain", "anaregents", "truthforcadau", "sofitees", "Simon_Hamaeth", "choconibbs", "CentralBulletin", "KronosStar", "HomelandIlluminations", "truccotrucco", "trollingsnark", "AbilaAllFaith", "AbilaPost", "SaveOurWildlands", "InternationalNews"], "slamrjamr": ["NewsOnlineToday", "MarcusDrymiau", "Officia1AbilaPost", "POK", "CentralBulletin", "HomelandIlluminations", "KronosStar", "SiaradSea", "truccotrucco", "AbilaPost", "brontes_riff", "SaveOurWildlands", "ReggieWassali", "InternationalNews"], "stolkfair": ["NewsOnlineToday", "protoGuy", "prettyRain", "FriendsOfKronos", "CentralBulletin", "HomelandIlluminations", "KronosStar", "AbilaPost", "megaMan", "Viktor-E", "InternationalNews"], "worldWatcher": ["NewsOnlineToday", "dangermice", "luvwool", "Officia1AbilaPost", "CentralBulletin", "HomelandIlluminations", "mamin", "KronosStar", "trollingsnark", "AbilaPost", "megaMan", "GreyCatCollectibles", "InternationalNews"], "Officia1AbilaPost": ["farmboy", "worldWatcher", "slamrjamr", "electricAvenue", "pinky", "joyce101"], "zengardener": ["stuffNstuff", "FriendsOfKronos", "choconibbs", "CentralBulletin", "trapanitweets", "HomelandIlluminations", "KronosStar", "hempRules", "AbilaPost", "megaMan", "brontes_riff", "martaO", "InternationalNews"], "hempRules": ["BlueVelvet", "siliconKing", "zengardener"], "joyce101": ["dangermice", "anaregents", "Officia1AbilaPost", "OnlytheTruth", "POK", "CentralBulletin", "HomelandIlluminations", "KronosStar", "footfingers", "AbilaPost", "megaMan", "brontes_riff", "InternationalNews", "AbilaPoliceDepartment", "ourcountryourrights"], "anaregents": ["brandonL", "lordWally", "jgrobannne", "joyce101"], "ReggieWassali": ["brain448", "slamrjamr", "klingon4real"], "ninjabob": ["NewsOnlineToday", "FriendsOfKronos", "CentralBulletin", "roger_roger", "HomelandIlluminations", "KronosStar", "panopticon", "AbilaPost", "megaMan", "praise111", "InternationalNews"], "stuffNstuff": ["zengardener"], "electricAvenue": ["Officia1AbilaPost", "Simon_Hamaeth", "CentralBulletin", "KronosStar", "HomelandIlluminations", "truccotrucco", "panopticon", "AbilaPost", "megaMan"], "SaveOurWildlands": ["jaques", "blueSunshine", "lordWally", "sarajane", "teresaJ", "luvMyPants", "soup4u", "slamrjamr", "wiseWords"], "footfingers": ["jaques", "muppiesRock", "brain448", "wiseWords", "joyce101"], "henri": ["choconibbs", "CentralBulletin", "roger_roger", "KronosStar", "HomelandIlluminations", "Sara_Nespola", "AbilaPost", "InternationalNews"], "farmboy": ["dangermice", "prettyRain", "NewsOnlineToday", "FriendsOfKronos", "truthforcadau", "Officia1AbilaPost", "CentralBulletin", "HomelandIlluminations", "KronosStar", "AbilaPost"], "truthforcadau": ["blueSunshine", "lordWally", "siliconKing", "farmboy", "luvMyPants"], "junk99902": ["sarajane"], "courage4life": ["NewsOnlineToday", "POK", "CentralBulletin", "HomelandIlluminations", "KronosStar", "truccotrucco", "trollingsnark", "AbilaPost", "megaMan", "InternationalNews"], "vonneka": ["NewsOnlineToday", "protoGuy", "OnlytheTruth", "CentralBulletin", "HomelandIlluminations", "KronosStar", "trollingsnark", "cleaningFish", "megaMan", "AbilaPost", "martaO", "Viktor-E", "starz1134"], "jaques": ["NewsOnlineToday", "FriendsOfKronos", "OnlytheTruth", "CentralBulletin", "roger_roger", "HomelandIlluminations", "KronosStar", "truccotrucco", "footfingers", "AbilaPost", "maha_Homeland", "SaveOurWildlands", "InternationalNews"], "brandonL": ["anaregents", "Simon_Hamaeth", "POK", "CentralBulletin", "HomelandIlluminations", "KronosStar", "SiaradSea", "AbilaPost", "megaMan", "jenny90210"], "jgrobannne": ["NewsOnlineToday", "anaregents", "ernieO", "roger_roger", "HomelandIlluminations", "KronosStar", "truccotrucco", "AbilaPost", "megaMan", "GreyCatCollectibles", "InternationalNews"], "pashmina887": ["sarajane"], "writinLazy": ["BlueVelvet"], "HomelandIlluminations": ["blueSunshine", "microBanana", "worldWatcher", "courage4life", "klingon4real", "brain448", "electricAvenue", "dtennent", "joyce101", "jaques", "muppiesRock", "wireHead1122", "siliconKing", "ninjabob", "stolkfair", "sarajane", "henri", "soup4u", "dolls4sale", "plasticParts", "zengardener", "wiseWords", "rrWine", "vonneka", "brandonL", "phantomagate", "slamrjamr", "sithLordJames", "lindyT", "vetsRock", "gardener4958", "BlueVelvet", "lordWally", "dragonRider1", "farmboy", "luvMyPants", "rnbwBrite", "pinky", "jgrobannne"], "OnlytheTruth": ["jaques", "klingon4real", "soup4u", "dolls4sale", "rrWine", "vonneka", "dtennent", "joyce101"], "KronosStar": ["blueSunshine", "microBanana", "worldWatcher", "courage4life", "klingon4real", "brain448", "electricAvenue", "joyce101", "jaques", "muppiesRock", "wireHead1122", "siliconKing", "sarajane", "stolkfair", "ninjabob", "henri", "soup4u", "dolls4sale", "plasticParts", "zengardener", "wiseWords", "rrWine", "vonneka", "brandonL", "phantomagate", "sithLordJames", "slamrjamr", "lindyT", "vetsRock", "gardener4958", "BlueVelvet", "lordWally", "dragonRider1", "teresaJ", "farmboy", "luvMyPants", "rnbwBrite", "pinky", "jgrobannne"], "trollingsnark": ["lordWally", "phantomagate", "worldWatcher", "courage4life", "wiseWords", "vonneka", "dtennent"], "HerraTomas": ["teresaJ"], "AbilaFireDept": ["teresaJ", "phantomagate", "microBanana", "dtennent"], "dangermice": ["wireHead1122", "teresaJ", "farmboy", "worldWatcher", "rrWine", "joyce101", "vetsRock"], "cleaningFish": ["vonneka", "pinky", "vetsRock"], "mamin": ["worldWatcher"], "kingWilly": ["blueSunshine"], "jenny90210": ["brandonL"], "GreyCatCollectibles": ["gardener4958", "BlueVelvet", "microBanana", "phantomagate", "worldWatcher", "dtennent", "dolls4sale", "jgrobannne"], "redisrad": ["phantomagate", "gardener4958", "dolls4sale", "siliconKing"], "NewsOnlineToday": ["blueSunshine", "microBanana", "worldWatcher", "courage4life", "klingon4real", "brain448", "dtennent", "jaques", "wireHead1122", "siliconKing", "stolkfair", "ninjabob", "dolls4sale", "plasticParts", "wiseWords", "vonneka", "phantomagate", "slamrjamr", "sithLordJames", "lindyT", "BlueVelvet", "dragonRider1", "teresaJ", "farmboy", "rnbwBrite", "pinky", "jgrobannne"], "AbilaAllFaith": ["teresaJ", "wireHead1122", "lordWally", "pinky"], "martaflores": ["sarajane"], "martaO": ["sarajane", "rnbwBrite", "zengardener", "wiseWords", "vonneka"], "AbilaPoliceDepartment": ["microBanana", "dragonRider1", "sarajane", "klingon4real", "sithLordJames", "joyce101"], "brewvebeenserved": ["rnbwBrite", "pinky"], "dtrejos": ["muppiesRock"], "trapanitweets": ["brain448", "zengardener"], "sofitees": ["BlueVelvet", "lordWally", "dragonRider1", "sarajane", "luvMyPants", "dolls4sale"], "michelleR": ["soup4u", "microBanana"], "hngohebo_ABILAPOST": ["plasticParts"], "SiaradSea": ["brandonL", "teresaJ", "slamrjamr", "plasticParts", "vetsRock"], "roger_roger": ["jaques", "BlueVelvet", "wireHead1122", "microBanana", "siliconKing", "sarajane", "dragonRider1", "ninjabob", "henri", "rrWine", "pinky", "jgrobannne"], "protoGuy": ["wireHead1122", "siliconKing", "stolkfair", "sarajane", "teresaJ", "luvMyPants", "dolls4sale", "wiseWords", "rrWine", "vonneka"], "megaMan": ["blueSunshine", "worldWatcher", "courage4life", "klingon4real", "electricAvenue", "dtennent", "joyce101", "siliconKing", "ninjabob", "stolkfair", "plasticParts", "zengardener", "wiseWords", "rrWine", "vonneka", "brandonL", "phantomagate", "lindyT", "gardener4958", "BlueVelvet", "rnbwBrite", "jgrobannne"], "Simon_Hamaeth": ["blueSunshine", "brandonL", "lordWally", "siliconKing", "electricAvenue"], "panopticon": ["muppiesRock", "ninjabob", "teresaJ", "brain448", "rrWine", "electricAvenue"], "Sara_Nespola": ["soup4u", "brain448", "teresaJ", "henri"], "prettyRain": ["lordWally", "microBanana", "dragonRider1", "stolkfair", "farmboy", "sithLordJames"], "ernieO": ["sithLordJames", "jgrobannne"], "brontes_riff": ["slamrjamr", "joyce101", "zengardener"], "soulofShi": ["rrWine"], "onl1neRecords": ["rnbwBrite"], "praise111": ["ninjabob", "wiseWords"], "surferMan": ["wireHead1122"], "grlPwrz505": ["phantomagate", "wiseWords"], "joyBubbles": ["dolls4sale"], "hennyhenhendrix": ["teresaJ", "vetsRock"], "MarcusDrymiau": ["slamrjamr", "microBanana"], "rockStar113": ["klingon4real"], "luvwool": ["worldWatcher"], "starz1134": ["vonneka"], "omgponies": ["wiseWords"]}